{
  "name": "Phind",
  "url": "https://phind.com",
  "description": "An AI-powered search engine built for developers. Phind searches the web in real time and synthesizes technical answers with code examples, documentation references, and relevant sources — no account required for basic usage.",
  "coreTask": "Get AI-generated answers to programming and technical questions with real-time web search and working code examples",
  "tags": [
    { "key": "category", "value": "AI" },
    { "key": "pricing", "value": "Freemium" },
    { "key": "type", "value": "Web App" },
    { "key": "data", "value": "Server-Side" }
  ]
}
